odoo/addons/stock_production_lot_firmware_version/README.rst
odoo/addons/stock_production_lot_firmware_version/__init__.py
odoo/addons/stock_production_lot_firmware_version/__manifest__.py
odoo/addons/stock_production_lot_firmware_version/i18n/ca.po
odoo/addons/stock_production_lot_firmware_version/i18n/de.po
odoo/addons/stock_production_lot_firmware_version/i18n/es.po
odoo/addons/stock_production_lot_firmware_version/i18n/fr.po
odoo/addons/stock_production_lot_firmware_version/i18n/it.po
odoo/addons/stock_production_lot_firmware_version/i18n/stock_production_lot_firmware_version.pot
odoo/addons/stock_production_lot_firmware_version/models/__init__.py
odoo/addons/stock_production_lot_firmware_version/models/stock.py
odoo/addons/stock_production_lot_firmware_version/readme/CONTRIBUTORS.rst
odoo/addons/stock_production_lot_firmware_version/readme/DESCRIPTION.rst
odoo/addons/stock_production_lot_firmware_version/readme/USAGE.rst
odoo/addons/stock_production_lot_firmware_version/static/description/icon.png
odoo/addons/stock_production_lot_firmware_version/static/description/index.html
odoo/addons/stock_production_lot_firmware_version/views/stock_view.xml
odoo13_addon_stock_production_lot_firmware_version-13.0.1.0.1.dev10.dist-info/METADATA
odoo13_addon_stock_production_lot_firmware_version-13.0.1.0.1.dev10.dist-info/WHEEL
odoo13_addon_stock_production_lot_firmware_version-13.0.1.0.1.dev10.dist-info/top_level.txt
odoo13_addon_stock_production_lot_firmware_version-13.0.1.0.1.dev10.dist-info/RECORD
